kiwi3d/__init__.py
kiwi3d/array_correspondence.py
kiwi3d/halfedges.py
kiwi3d/per_face_normals.py
kiwi3d/triangle_triangle_adjacency.py
kiwi3d-0.1.2.dist-info/METADATA
kiwi3d-0.1.2.dist-info/WHEEL
kiwi3d-0.1.2.dist-info/RECORD
