Metadata-Version: 2.1
Name: kiwi3d
Version: 0.1.2
Summary: 
Author: Wonjong Jang
Author-email: wonjong@postech.ac.kr
Requires-Python: >=3.9,<4.0
Classifier: Programming Language :: Python :: 3
Classifier: Programming Language :: Python :: 3.9
Classifier: Programming Language :: Python :: 3.10
Classifier: Programming Language :: Python :: 3.11
Classifier: Programming Language :: Python :: 3.12
Requires-Dist: torch (>=1.10.1)
